kasperskytip/__init__.py
kasperskytip/exceptions.py
kasperskytip/kasperskytip.py
kasperskytip-1.0.dist-info/METADATA
kasperskytip-1.0.dist-info/WHEEL
kasperskytip-1.0.dist-info/top_level.txt
kasperskytip-1.0.dist-info/RECORD
