Metadata-Version: 2.1
Name: kasperskytip
Version: 1.0
Summary: Kaspersky TIP unofficial API for Python
Home-page: https://github.com/clienthold/kaspersky-tip
Author: Dmitry Kondrashov
Keywords: api kaspersky antivirus malware scan
Requires-Python: >=3.7, <4
Requires-Dist: requests
Requires-Dist: datetime
Requires-Dist: validators
